__init__.py
dccQuantities.py
dccQuantitiesConfiguration.py
dccQuantitiesPlot.py
dccQuantities-1.4.6.dist-info/LICENSE
dccQuantities-1.4.6.dist-info/METADATA
dccQuantities-1.4.6.dist-info/WHEEL
dccQuantities-1.4.6.dist-info/top_level.txt
dccQuantities-1.4.6.dist-info/RECORD
