Metadata-Version: 2.1
Name: dccQuantities
Version: 1.4.6
Summary: Python classes for working with DDC calibration data
Home-page: https://gitlab1.ptb.de/digitaldynamicmeasurement/dccQuantities
Author: Benedikt Seeger, Vanessa Stehr, Thomas Bruns
Author-email: benedikt.seeger@ptb.de
License: LGPL-2.1-or-later
Requires-Python: >=3.10
License-File: LICENSE
Requires-Dist: numpy
Requires-Dist: scipy
Requires-Dist: uncertainties
Requires-Dist: requests
Requires-Dist: pylatexenc
Requires-Dist: odfpy
Requires-Dist: openpyxl
Requires-Dist: pandas
Requires-Dist: dsiUnits
Requires-Dist: dccXMLJSONConv
Provides-Extra: dccquantitiesplot
Requires-Dist: bokeh ; extra == 'dccquantitiesplot'
Provides-Extra: testing
Requires-Dist: pytest ==7.4.1 ; extra == 'testing'
Requires-Dist: pytest-cov ==4.1.0 ; extra == 'testing'
